{
  "hyuu": {
    "username": "hyuu",
    "password": "XATAN02KO5",
    "createdAt": "2025-06-28T08:47:29.872Z",
    "createdBy": "hiyuux"
  },
  "admin": {
    "username": "admin",
    "password": "XATAELY4NE",
    "createdAt": "2025-06-29T16:27:55.392Z",
    "createdBy": "Xatanicvxii"
  },
  "BesokBisaPake": {
    "username": "BesokBisaPake",
    "password": "XATA4HH569",
    "createdAt": "2025-06-29T17:16:04.673Z",
    "createdBy": "Xatanicvxii"
  },
  "AdminPenjaga": {
    "username": "AdminPenjaga",
    "password": "XATANHXPD8",
    "createdAt": "2025-06-30T05:15:57.658Z",
    "createdBy": "Xatanicvxii"
  },
  "makkau": {
    "username": "makkau",
    "password": "XATAOAKRVZ",
    "createdAt": "2025-06-30T05:28:45.396Z",
    "createdBy": "xtrxbarrtzy"
  },
  "pribadi": {
    "username": "pribadi",
    "password": "XATAQU33Y2",
    "createdAt": "2025-06-30T05:33:39.297Z",
    "createdBy": "Xmodssxii"
  },
  "Thomzz": {
    "username": "Thomzz",
    "password": "XATA39CP13",
    "createdAt": "2025-06-30T05:33:44.121Z",
    "createdBy": "Thomzzkece"
  },
  "marczz": {
    "username": "marczz",
    "password": "XATAXJH1BR",
    "createdAt": "2025-06-30T05:35:32.505Z",
    "createdBy": "MarczzReal"
  },
  "nuxbuydixero": {
    "username": "nuxbuydixero",
    "password": "XATAHT7AGJ",
    "createdAt": "2025-06-30T05:36:14.438Z",
    "createdBy": "Xerotamvan"
  },
  "Anuu": {
    "username": "Anuu",
    "password": "XATAVZYVK1",
    "createdAt": "2025-06-30T05:37:04.447Z",
    "createdBy": "AlwaysNuuu"
  },
  "yuji": {
    "username": "yuji",
    "password": "XATAO6XAXG",
    "createdAt": "2025-06-30T05:38:51.893Z",
    "createdBy": "Lixxishere"
  },
  "ikra anj": {
    "username": "ikra anj",
    "password": "XATA8N1FSW",
    "createdAt": "2025-06-30T05:44:13.530Z",
    "createdBy": "Thomzzkece"
  },
  "reza": {
    "username": "reza",
    "password": "XATA5H130G",
    "createdAt": "2025-06-30T05:46:13.708Z",
    "createdBy": "TheGodWolf"
  },
  "rifbuydixero": {
    "username": "rifbuydixero",
    "password": "XATAG4EQEH",
    "createdAt": "2025-06-30T05:49:46.807Z",
    "createdBy": "Xerotamvan"
  },
  "denz": {
    "username": "denz",
    "password": "XATA0EJI6W",
    "createdAt": "2025-06-30T05:52:55.894Z",
    "createdBy": "MarczzReal"
  },
  "plato": {
    "username": "plato",
    "password": "XATAZGU3E2",
    "createdAt": "2025-06-30T05:54:00.727Z",
    "createdBy": "apatukamm"
  },
  "dikzz": {
    "username": "dikzz",
    "password": "XATA301527",
    "createdAt": "2025-06-30T05:55:18.989Z",
    "createdBy": "AboutVils"
  },
  "denzbuydixero": {
    "username": "denzbuydixero",
    "password": "XATATRV8KD",
    "createdAt": "2025-06-30T05:56:11.698Z",
    "createdBy": "Xerotamvan"
  },
  "qisz": {
    "username": "qisz",
    "password": "XATABJEE1N",
    "createdAt": "2025-06-30T05:56:12.202Z",
    "createdBy": "AboutVils"
  },
  "fian": {
    "username": "fian",
    "password": "XATAV82CL9",
    "createdAt": "2025-06-30T05:58:40.194Z",
    "createdBy": "Rasyya_Real"
  },
  "Dzultampan": {
    "username": "Dzultampan",
    "password": "XATA49TSGY",
    "createdAt": "2025-06-30T05:59:06.693Z",
    "createdBy": "ditxstur"
  },
  "Nay": {
    "username": "Nay",
    "password": "XATAUAY1XQ",
    "createdAt": "2025-06-30T06:00:01.342Z",
    "createdBy": "Rasyya_Real"
  },
  "arya": {
    "username": "arya",
    "password": "XATAMH5FTO",
    "createdAt": "2025-06-30T06:01:12.224Z",
    "createdBy": "Ocongreal"
  },
  "Denz1": {
    "username": "Denz1",
    "password": "XATA4ZM1E1",
    "createdAt": "2025-06-30T06:01:23.737Z",
    "createdBy": "xwarrx"
  },
  "manzzy": {
    "username": "manzzy",
    "password": "XATA8R5XRG",
    "createdAt": "2025-06-30T06:02:01.252Z",
    "createdBy": "Rasyya_Real"
  },
  "raky": {
    "username": "raky",
    "password": "XATAUWTDM5",
    "createdAt": "2025-06-30T06:02:16.192Z",
    "createdBy": "rakyxz"
  },
  "bakso": {
    "username": "bakso",
    "password": "XATA3J7YXJ",
    "createdAt": "2025-06-30T06:02:41.750Z",
    "createdBy": "vanzmods2"
  },
  "xan": {
    "username": "xan",
    "password": "XATAK7IJR3",
    "createdAt": "2025-06-30T06:03:17.799Z",
    "createdBy": "Xcioo"
  },
  "ocong": {
    "username": "ocong",
    "password": "XATARGI2OU",
    "createdAt": "2025-06-30T06:03:39.237Z",
    "createdBy": "Ocongreal"
  },
  "kaizen": {
    "username": "kaizen",
    "password": "XATAXWI0XU",
    "createdAt": "2025-06-30T06:10:18.321Z",
    "createdBy": "MarczzReal"
  },
  "Renz": {
    "username": "Renz",
    "password": "XATAC4Y6Y7",
    "createdAt": "2025-06-30T06:10:23.750Z",
    "createdBy": "ditxstur"
  },
  "chelz": {
    "username": "chelz",
    "password": "XATAE6LK9B",
    "createdAt": "2025-06-30T06:10:29.687Z",
    "createdBy": "MarczzReal"
  },
  "kuri": {
    "username": "kuri",
    "password": "XATA667I3Z",
    "createdAt": "2025-06-30T06:10:35.795Z",
    "createdBy": "Kuriii4trre"
  },
  "Jarz": {
    "username": "Jarz",
    "password": "XATAAYH3XY",
    "createdAt": "2025-06-30T06:13:27.999Z",
    "createdBy": "Thomzzkece"
  },
  "kirito": {
    "username": "kirito",
    "password": "XATA6V8OX3",
    "createdAt": "2025-06-30T06:17:28.016Z",
    "createdBy": "vanzmods2"
  },
  "Rizz": {
    "username": "Rizz",
    "password": "XATALFHA3J",
    "createdAt": "2025-06-30T06:19:58.144Z",
    "createdBy": "kepoomemwk"
  },
  "aditphp": {
    "username": "aditphp",
    "password": "XATA519DPU",
    "createdAt": "2025-06-30T06:21:05.558Z",
    "createdBy": "Lixxishere"
  },
  "vira": {
    "username": "vira",
    "password": "XATASV00O3",
    "createdAt": "2025-06-30T06:21:17.580Z",
    "createdBy": "Farrasreall"
  },
  "dapa": {
    "username": "dapa",
    "password": "XATAUOGV5G",
    "createdAt": "2025-06-30T06:21:18.516Z",
    "createdBy": "kepoomemwk"
  },
  "Ditxz": {
    "username": "Ditxz",
    "password": "XATAG6PVAA",
    "createdAt": "2025-06-30T06:21:56.515Z",
    "createdBy": "ditxstur"
  },
  "MURBUGHAMZXYZX": {
    "username": "MURBUGHAMZXYZX",
    "password": "XATALHIWNF",
    "createdAt": "2025-06-30T06:21:57.822Z",
    "createdBy": "Hamzvcx"
  },
  "Bajisantol": {
    "username": "Bajisantol",
    "password": "XATAJO8RSF",
    "createdAt": "2025-06-30T06:22:33.903Z",
    "createdBy": "vipertryy1"
  },
  "xata": {
    "username": "xata",
    "password": "XATAP9IDBT",
    "createdAt": "2025-06-30T06:23:17.985Z",
    "createdBy": "Xatanicvxii"
  },
  "david": {
    "username": "david",
    "password": "XATA9SN48A",
    "createdAt": "2025-06-30T06:24:19.939Z",
    "createdBy": "xwarrx"
  },
  "babay": {
    "username": "babay",
    "password": "XATAPAPM1F",
    "createdAt": "2025-06-30T06:24:36.442Z",
    "createdBy": "HAANNHZ"
  },
  "Brando": {
    "username": "Brando",
    "password": "XATA0DPA2H",
    "createdAt": "2025-06-30T06:26:10.961Z",
    "createdBy": "DELION9Q"
  },
  "didibuydixero": {
    "username": "didibuydixero",
    "password": "XATA3OK6QN",
    "createdAt": "2025-06-30T06:26:30.146Z",
    "createdBy": "Xerotamvan"
  },
  "adli": {
    "username": "adli",
    "password": "XATAISTTG9",
    "createdAt": "2025-06-30T06:26:52.722Z",
    "createdBy": "sultanosmed"
  },
  "aldi": {
    "username": "aldi",
    "password": "XATA5X8N06",
    "createdAt": "2025-06-30T06:26:58.892Z",
    "createdBy": "sultanosmed"
  },
  "kiora": {
    "username": "kiora",
    "password": "XATA524MDC",
    "createdAt": "2025-06-30T06:27:33.037Z",
    "createdBy": "DELION9Q"
  },
  "kaezar": {
    "username": "kaezar",
    "password": "XATAL4QM85",
    "createdAt": "2025-06-30T06:29:13.449Z",
    "createdBy": "DELION9Q"
  },
  "dealuvluv": {
    "username": "dealuvluv",
    "password": "XATAMYZSBX",
    "createdAt": "2025-06-30T06:30:00.451Z",
    "createdBy": "laiqxX"
  },
  "dimass": {
    "username": "dimass",
    "password": "XATA3JFXVT",
    "createdAt": "2025-06-30T06:31:54.885Z",
    "createdBy": "xwarrx"
  },
  "Vanguard": {
    "username": "Vanguard",
    "password": "XATAXC4S71",
    "createdAt": "2025-06-30T06:32:23.336Z",
    "createdBy": "xwarrx"
  },
  "BloodsKil": {
    "username": "BloodsKil",
    "password": "XATAP6C25W",
    "createdAt": "2025-06-30T06:33:34.614Z",
    "createdBy": "xwarrx"
  },
  "nadnad": {
    "username": "nadnad",
    "password": "XATASYTWMH",
    "createdAt": "2025-06-30T06:34:32.139Z",
    "createdBy": "xwarrx"
  },
  "kimX": {
    "username": "kimX",
    "password": "XATA86XY92",
    "createdAt": "2025-06-30T06:35:09.885Z",
    "createdBy": "sultanosmed"
  },
  "buyer1": {
    "username": "buyer1",
    "password": "XATAR5QKT8",
    "createdAt": "2025-06-30T06:39:08.422Z",
    "createdBy": "xwarrx"
  },
  "riyan": {
    "username": "riyan",
    "password": "XATAINOBWP",
    "createdAt": "2025-06-30T06:39:29.196Z",
    "createdBy": "sultanosmed"
  },
  "oke": {
    "username": "oke",
    "password": "XATAZ44HFP",
    "createdAt": "2025-06-30T06:40:36.588Z",
    "createdBy": "Rasyya_Real"
  },
  "ZVXVZ": {
    "username": "ZVXVZ",
    "password": "XATAMFY7NJ",
    "createdAt": "2025-06-30T06:43:20.587Z",
    "createdBy": "AlwaysKarzz"
  },
  "nyaik": {
    "username": "nyaik",
    "password": "XATAKTPCW5",
    "createdAt": "2025-06-30T06:43:31.882Z",
    "createdBy": "VikeXi"
  },
  "selax": {
    "username": "selax",
    "password": "XATAH8311S",
    "createdAt": "2025-06-30T06:46:22.809Z",
    "createdBy": "kepoomemwk"
  },
  "firza": {
    "username": "firza",
    "password": "XATA30OMHQ",
    "createdAt": "2025-06-30T06:47:16.928Z",
    "createdBy": "Junzaja"
  },
  "buyer1firza": {
    "username": "buyer1firza",
    "password": "XATAQTDRX4",
    "createdAt": "2025-06-30T06:47:43.485Z",
    "createdBy": "Junzaja"
  },
  "buyer2firza": {
    "username": "buyer2firza",
    "password": "XATAAEIJEZ",
    "createdAt": "2025-06-30T06:48:00.995Z",
    "createdBy": "Junzaja"
  },
  "dirga": {
    "username": "dirga",
    "password": "XATAUSK622",
    "createdAt": "2025-06-30T08:40:36.831Z",
    "createdBy": "kepoomemwk"
  },
  "zaro": {
    "username": "zaro",
    "password": "XATAICU2Y4",
    "createdAt": "2025-06-30T08:40:36.833Z",
    "createdBy": "DELION9Q"
  },
  "repay": {
    "username": "repay",
    "password": "XATAJQ6AA6",
    "createdAt": "2025-06-30T08:40:37.663Z",
    "createdBy": "TheGodWolf"
  },
  "Manzy": {
    "username": "Manzy",
    "password": "XATAALC9LV",
    "createdAt": "2025-06-30T08:40:37.663Z",
    "createdBy": "themanzzy"
  },
  "Lixx": {
    "username": "Lixx",
    "password": "XATAL0FLB5",
    "createdAt": "2025-06-30T08:40:38.197Z",
    "createdBy": "Lixxishere"
  },
  "aqib": {
    "username": "aqib",
    "password": "XATA5I0MV6",
    "createdAt": "2025-06-30T08:40:38.884Z",
    "createdBy": "aqib1213"
  },
  "buyyer": {
    "username": "buyyer",
    "password": "XATA4GOZCE",
    "createdAt": "2025-06-30T08:40:41.385Z",
    "createdBy": "Junzaja"
  },
  "xzen": {
    "username": "xzen",
    "password": "XATAZ8SR3Z",
    "createdAt": "2025-06-30T08:45:40.264Z",
    "createdBy": "xwarrx"
  },
  "Zxrex Ganteng kek pler": {
    "username": "Zxrex Ganteng kek pler",
    "password": "XATA1GCLAT",
    "createdAt": "2025-06-30T08:50:37.751Z",
    "createdBy": "Thomzzkece"
  },
  "shakaa": {
    "username": "shakaa",
    "password": "XATAK0D60H",
    "createdAt": "2025-06-30T08:53:05.087Z",
    "createdBy": "xwarrx"
  },
  "Fri": {
    "username": "Fri",
    "password": "XATAOAJ5OS",
    "createdAt": "2025-06-30T09:01:08.813Z",
    "createdBy": "kepoomemwk"
  },
  "windi": {
    "username": "windi",
    "password": "XATAG764QX",
    "createdAt": "2025-06-30T09:02:09.261Z",
    "createdBy": "xwarrx"
  },
  "kimi": {
    "username": "kimi",
    "password": "XATACXCC9O",
    "createdAt": "2025-06-30T09:04:58.961Z",
    "createdBy": "Kimimarutzy"
  },
  "dakoy": {
    "username": "dakoy",
    "password": "XATAD7XUM3",
    "createdAt": "2025-06-30T09:08:28.988Z",
    "createdBy": "xwarrx"
  },
  "apisrajagula": {
    "username": "apisrajagula",
    "password": "XATA8BB0MK",
    "createdAt": "2025-06-30T09:17:35.225Z",
    "createdBy": "xwarrx"
  },
  "Zidan": {
    "username": "Zidan",
    "password": "XATAMLAGLJ",
    "createdAt": "2025-06-30T09:17:35.226Z",
    "createdBy": "DxyCalix"
  },
  "bids": {
    "username": "bids",
    "password": "XATAZG3884",
    "createdAt": "2025-06-30T09:17:35.227Z",
    "createdBy": "kepoomemwk"
  },
  "novaclient": {
    "username": "novaclient",
    "password": "XATAHY5Q5B",
    "createdAt": "2025-06-30T09:17:35.227Z",
    "createdBy": "xtrxnovatryy"
  },
  "harunbuydixero": {
    "username": "harunbuydixero",
    "password": "XATAWNWMOM",
    "createdAt": "2025-06-30T09:17:54.509Z",
    "createdBy": "Xerotamvan"
  },
  "murbugzidan": {
    "username": "murbugzidan",
    "password": "XATA4MUWCL",
    "createdAt": "2025-06-30T09:18:44.902Z",
    "createdBy": "DxyCalix"
  },
  "nyahsuper": {
    "username": "nyahsuper",
    "password": "XATA9KGE8B",
    "createdAt": "2025-06-30T09:19:07.929Z",
    "createdBy": "DxyCalix"
  },
  "danzzy": {
    "username": "danzzy",
    "password": "XATAUP3M6L",
    "createdAt": "2025-06-30T09:20:05.076Z",
    "createdBy": "DxyCalix"
  },
  "khowgila": {
    "username": "khowgila",
    "password": "XATATDRFTB",
    "createdAt": "2025-06-30T09:22:38.101Z",
    "createdBy": "Zyxwaw"
  },
  "FaaTzyy": {
    "username": "FaaTzyy",
    "password": "XATAUJHBBK",
    "createdAt": "2025-06-30T09:25:34.895Z",
    "createdBy": "yesussid"
  }
}